{	
	"name": "lopper forge",
    "type": "GenericCrafter",
    "description": "forges copper & lead",
    "health": 100,
	"size": 2,
	"hasItems": true,
	"itemCapacity": 10,	
	"craftTime": 20,
	"craftEffect": "smeltsmoke",
	"updateEffect": "none",
	"consumes": {
		"items": {
			"items": [
               "copper/1",
			   "lead/1"
			]
		}
	},
	"requirements": [
        "compressed-copper/50",
        "compressed-lead/25"
	],
	"category": "crafting",
	"research": "lead-compressor",
	"outputItem": "lopper/1"
}